gotchatwitter/__init__.py
gotchatwitter/gotchatwitter.py
gotchatwitter/json2csv.py
gotchatwitter/loader_utils.py
gotchatwitter/notifier_print.py
gotchatwitter/notifier_pushbullet.py
gotchatwitter/parser_threads.py
gotchatwitter/parser_timeline.py
gotchatwitter/parser_utils.py
gotchatwitter-0.1.26.dist-info/DESCRIPTION.rst
gotchatwitter-0.1.26.dist-info/METADATA
gotchatwitter-0.1.26.dist-info/RECORD
gotchatwitter-0.1.26.dist-info/WHEEL
gotchatwitter-0.1.26.dist-info/metadata.json
gotchatwitter-0.1.26.dist-info/top_level.txt
gotchatwitter-0.1.26.dist-info/zip-safe
